sufetron/__init__.py
sufetron/guard.py
sufetron-0.1.dist-info/licenses/LICENSE
sufetron-0.1.dist-info/METADATA
sufetron-0.1.dist-info/WHEEL
sufetron-0.1.dist-info/top_level.txt
sufetron-0.1.dist-info/RECORD
