Metadata-Version: 2.4
Name: sufetron
Version: 0.1
Summary: AI-powered HTTP request firewall for Flask apps
Author: ghayth-bouzayeni
Author-email: bouzayanighayth@gmail.com
Classifier: Programming Language :: Python :: 3
Classifier: Operating System :: OS Independent
Requires-Python: >=3.6
License-File: LICENSE
Requires-Dist: Flask
Requires-Dist: requests
Dynamic: author
Dynamic: author-email
Dynamic: classifier
Dynamic: license-file
Dynamic: requires-dist
Dynamic: requires-python
Dynamic: summary
